{
	"$schema": "https://unpkg.com/jsrepo@1.45.0/schemas/registry-config.json",
	"dirs": ["./src/lib/components/blocks", "./src/lib/components", "./src"],
	"doNotListBlocks": [],
	"doNotListCategories": [],
	"listBlocks": [],
	"listCategories": [
		"call-to-action",
		"comparator",
		"contact",
		"content",
		"faq",
		"features",
		"footer",
		"header",
		"hero",
		"login",
		"logo-cloud",
		"pricing",
		"signup",
		"stats",
		"team",
		"testimonials"
	],
	"excludeDeps": [],
	"includeBlocks": [],
	"includeCategories": [
		"web",
		"ui",
		"magic",
		"lib",
		"call-to-action",
		"comparator",
		"contact",
		"content",
		"faq",
		"features",
		"footer",
		"header",
		"hero",
		"login",
		"logo-cloud",
		"pricing",
		"signup",
		"stats",
		"team",
		"testimonials"
	],
	"excludeBlocks": ["index", "all_blocks"],
	"excludeCategories": [],
	"preview": true
}
